Workbook

Sheet Assumptions
A1: ASSUMPTIONS
A3: PRICING TIERS
A4: Metric | B4: Value
A5: Tier 1 Setup Fee | B5: 997
A6: Tier 1 Monthly Fee | B6: 149
A7: Tier 2 Setup Fee | B7: 1997
A8: Tier 2 Monthly Fee | B8: 249
A9: Tier 3 Setup Fee | B9: 3497
A10: Tier 3 Monthly Fee | B10: 397
A12: TIER MIX (% of closes)
A13: Tier 1 % | B13: 0.6
A14: Tier 2 % | B14: 0.3
A15: Tier 3 % | B15: 0.1
A17: MONTHLY COSTS
A18: Claude Max | B18: 200
A19: Lovable | B19: 50
A20: Instantly.ai | B20: 37
A21: Google Workspace | B21: 14
A22: Outscraper | B22: 10
A23: Domains | B23: 3
A24: TOTAL MONTHLY COSTS | B24: =SUM(B18:B23)
A26: EMAIL CAMPAIGN | B26: 100
A27: Emails per week (target) | B27: 0.05
A28: Reply rate (conservative) | B28: 0.1
A29: Reply rate (realistic) | B29: 0.15
A30: Reply rate (optimistic) | B30: 0.2
A31: Close rate on replies
B32: 0.05
A33: BUSINESS METRICS | B33: 20
A34: Monthly churn rate | B34: 100
A35: Hours per week (owner)
A36: Hourly value target

Sheet Week-by-Week
A1: 12-WEEK PROJECTION
A2: Week | B2: Week 1 | C2: Week 2 | D2: Week 3 | E2: Week 4 | F2: Week 5 | G2: Week 6 | H2: Week 7 | I2: Week 8 | J2: Week 9 | K2: Week 10 | L2: Week 11 | M2: Week 12
A3: Leads scraped | B3: 20 | C3: 27 | D3: 34 | E3: 41 | F3: 48 | G3: 55 | H3: 62 | I3: 69 | J3: 76 | K3: 83 | L3: 90 | M3: 97
A4: Demo sites built | B4: =ROUND(B3*0.5,0) | C4: =ROUND(C3*0.5,0) | D4: =ROUND(D3*0.5,0) | E4: =ROUND(E3*0.5,0) | F4: =ROUND(F3*0.5,0) | G4: =ROUND(G3*0.5,0) | H4: =ROUND(H3*0.5,0) | I4: =ROUND(I3*0.5,0) | ... M4: =ROUND(M3*0.5,0)
A5: Emails sent | B5: 0 | C5: 0 | D5: 20 | E5: 35 | F5: 50 | G5: 65 | H5: 80 | I5: 95 | J5: 100 | K5: 100 | L5: 100 | M5: 100
A6: Expected replies | B6: =ROUND(B5*Assumptions!$B$28,0) | C6: =ROUND(C5*Assumptions!$B$28,0) | D6: =ROUND(D5*Assumptions!$B$28,0) | E6: =ROUND(E5*Assumptions!$B$28,0) | F6: =ROUND(F5*Assumptions!$B$28,0) | G6: =ROUND(G5*Assumptions!$B$28,0) | H6: =ROUND(H5*Assumptions!$B$28,0) | I6: =ROUND(I5*Assumptions!$B$28,0) | ... M6: =ROUND(M5*Assumptions!$B$28,0)
A7: Expected closes | B7: =ROUND(B6*Assumptions!$B$30,0) | C7: =ROUND(C6*Assumptions!$B$30,0) | D7: =ROUND(D6*Assumptions!$B$30,0) | E7: =ROUND(E6*Assumptions!$B$30,0) | F7: =ROUND(F6*Assumptions!$B$30,0) | G7: =ROUND(G6*Assumptions!$B$30,0) | H7: =ROUND(H6*Assumptions!$B$30,0) | I7: =ROUND(I6*Assumptions!$B$30,0) | ... M7: =ROUND(M6*Assumptions!$B$30,0)
A8: New setup revenue | B8: =B7*(Assumptions!$B$5*Assumptions!$B$13+Assumptions!$B$7*Assumptions!$B$14+Assumptions!$B$9*Assumptions!$B$15) | C8: =C7*(Assumptions!$B$5*Assumptions!$B$13+Assumptions!$B$7*Assumptions!$B$14+Assumptions!$B$9*Assumptions!$B$15) | D8: =D7*(Assumptions!$B$5*Assumptions!$B$13+Assumptions!$B$7*Assumptions!$B$14+Assumptions!$B$9*Assumptions!$B$15) | E8: =E7*(Assumptions!$B$5*Assumptions!$B$13+Assumptions!$B$7*Assumptions!$B$14+Assumptions!$B$9*Assumptions!$B$15) | F8: =F7*(Assumptions!$B$5*Assumptions!$B$13+Assumptions!$B$7*Assumptions!$B$14+Assumptions!$B$9*Assumptions!$B$15) | G8: =G7*(Assumptions!$B$5*Assumptions!$B$13+Assumptions!$B$7*Assumptions!$B$14+Assumptions!$B$9*Assumptions!$B$15) | H8: =H7*(Assumptions!$B$5*Assumptions!$B$13+Assumptions!$B$7*Assumptions!$B$14+Assumptions!$B$9*Assumptions!$B$15) | I8: =I7*(Assumptions!$B$5*Assumptions!$B$13+Assumptions!$B$7*Assumptions!$B$14+Assumptions!$B$9*Assumptions!$B$15) | ... M8: =M7*(Assumptions!$B$5*Assumptions!$B$13+Assumptions!$B$7*Assumptions!$B$14+Assumptions!$B$9*Assumptions!$B$15)
A9: New MRR added | B9: =B7*(Assumptions!$B$6*Assumptions!$B$13+Assumptions!$B$8*Assumptions!$B$14+Assumptions!$B$10*Assumptions!$B$15) | C9: =C7*(Assumptions!$B$6*Assumptions!$B$13+Assumptions!$B$8*Assumptions!$B$14+Assumptions!$B$10*Assumptions!$B$15) | D9: =D7*(Assumptions!$B$6*Assumptions!$B$13+Assumptions!$B$8*Assumptions!$B$14+Assumptions!$B$10*Assumptions!$B$15) | E9: =E7*(Assumptions!$B$6*Assumptions!$B$13+Assumptions!$B$8*Assumptions!$B$14+Assumptions!$B$10*Assumptions!$B$15) | F9: =F7*(Assumptions!$B$6*Assumptions!$B$13+Assumptions!$B$8*Assumptions!$B$14+Assumptions!$B$10*Assumptions!$B$15) | G9: =G7*(Assumptions!$B$6*Assumptions!$B$13+Assumptions!$B$8*Assumptions!$B$14+Assumptions!$B$10*Assumptions!$B$15) | H9: =H7*(Assumptions!$B$6*Assumptions!$B$13+Assumptions!$B$8*Assumptions!$B$14+Assumptions!$B$10*Assumptions!$B$15) | I9: =I7*(Assumptions!$B$6*Assumptions!$B$13+Assumptions!$B$8*Assumptions!$B$14+Assumptions!$B$10*Assumptions!$B$15) | ... M9: =M7*(Assumptions!$B$6*Assumptions!$B$13+Assumptions!$B$8*Assumptions!$B$14+Assumptions!$B$10*Assumptions!$B$15)
A10: Cumulative clients | B10: =B7 | C10: =B10+C7-ROUND(B10*Assumptions!$B$32,0) | D10: =C10+D7-ROUND(C10*Assumptions!$B$32,0) | E10: =D10+E7-ROUND(D10*Assumptions!$B$32,0) | F10: =E10+F7-ROUND(E10*Assumptions!$B$32,0) | G10: =F10+G7-ROUND(F10*Assumptions!$B$32,0) | H10: =G10+H7-ROUND(G10*Assumptions!$B$32,0) | I10: =H10+I7-ROUND(H10*Assumptions!$B$32,0) | J10: =I10+J7-ROUND(I10*Assumptions!$B$32,0) | ... M10: =L10+M7-ROUND(L10*Assumptions!$B$32,0)
A11: Cumulative MRR | B11: =B9 | C11: =B11+C9-ROUND(B11*Assumptions!$B$32,0) | D11: =C11+D9-ROUND(C11*Assumptions!$B$32,0) | E11: =D11+E9-ROUND(D11*Assumptions!$B$32,0) | F11: =E11+F9-ROUND(E11*Assumptions!$B$32,0) | G11: =F11+G9-ROUND(F11*Assumptions!$B$32,0) | H11: =G11+H9-ROUND(G11*Assumptions!$B$32,0) | I11: =H11+I9-ROUND(H11*Assumptions!$B$32,0) | J11: =I11+J9-ROUND(I11*Assumptions!$B$32,0) | ... M11: =L11+M9-ROUND(L11*Assumptions!$B$32,0)
A12: Weekly revenue | B12: =B8+B11/4.33 | C12: =C8+C11/4.33 | D12: =D8+D11/4.33 | E12: =E8+E11/4.33 | F12: =F8+F11/4.33 | G12: =G8+G11/4.33 | H12: =H8+H11/4.33 | I12: =I8+I11/4.33 | ... M12: =M8+M11/4.33
A13: Weekly expenses | B13: =Assumptions!$B$24/4.33 | C13: =Assumptions!$B$24/4.33 | D13: =Assumptions!$B$24/4.33 | E13: =Assumptions!$B$24/4.33 | F13: =Assumptions!$B$24/4.33 | G13: =Assumptions!$B$24/4.33 | H13: =Assumptions!$B$24/4.33 | I13: =Assumptions!$B$24/4.33 | ... M13: =Assumptions!$B$24/4.33
A14: Weekly profit | B14: =B12-B13 | C14: =C12-C13 | D14: =D12-D13 | E14: =E12-E13 | F14: =F12-F13 | G14: =G12-G13 | H14: =H12-H13 | I14: =I12-I13 | ... M14: =M12-M13

Sheet 3 Scenarios
A1: 90-DAY SCENARIO ANALYSIS
B2: Conservative | C2: Realistic | D2: Optimistic
A3: Reply Rate | B3: 5% | C3: 10% | D3: 15%
A4: Close Rate | B4: 20% | C4: 20% | D4: 20%
A6: MONTH 1 RESULTS
A7: Total clients acquired
A8: Total setup revenue
A9: Ending MRR | B9: 2 | C9: 2 | D9: 3
A10: Total revenue | B10: =B9*(Assumptions!$B$5*Assumptions!$B$13+Assumptions!$B$7*Assumptions!$B$14+Assumptions!$B$9*Assumptions!$B$15) | C10: =C9*(Assumptions!$B$5*Assumptions!$B$13+Assumptions!$B$7*Assumptions!$B$14+Assumptions!$B$9*Assumptions!$B$15) | D10: =D9*(Assumptions!$B$5*Assumptions!$B$13+Assumptions!$B$7*Assumptions!$B$14+Assumptions!$B$9*Assumptions!$B$15)
A11: Total expenses | B11: =B9*(Assumptions!$B$6*Assumptions!$B$13+Assumptions!$B$8*Assumptions!$B$14+Assumptions!$B$10*Assumptions!$B$15) | C11: =C9*(Assumptions!$B$6*Assumptions!$B$13+Assumptions!$B$8*Assumptions!$B$14+Assumptions!$B$10*Assumptions!$B$15) | D11: =D9*(Assumptions!$B$6*Assumptions!$B$13+Assumptions!$B$8*Assumptions!$B$14+Assumptions!$B$10*Assumptions!$B$15)
A12: Net profit | B12: =B11 | C12: =C11 | D12: =D11
B13: =B10+B11 | C13: =C10+C11 | D13: =D10+D11
A14: MONTH 2 | B14: =Assumptions!$B$24 | C14: =Assumptions!$B$24 | D14: =Assumptions!$B$24
A15: Total clients acquired | B15: 4 | C15: 4 | D15: 6
A16: Total setup revenue | B16: =B15*(Assumptions!$B$5*Assumptions!$B$13+Assumptions!$B$7*Assumptions!$B$14+Assumptions!$B$9*Assumptions!$B$15) | C16: =C15*(Assumptions!$B$5*Assumptions!$B$13+Assumptions!$B$7*Assumptions!$B$14+Assumptions!$B$9*Assumptions!$B$15) | D16: =D15*(Assumptions!$B$5*Assumptions!$B$13+Assumptions!$B$7*Assumptions!$B$14+Assumptions!$B$9*Assumptions!$B$15)
A17: Ending MRR | B17: =B15*(Assumptions!$B$6*Assumptions!$B$13+Assumptions!$B$8*Assumptions!$B$14+Assumptions!$B$10*Assumptions!$B$15) | C17: =C15*(Assumptions!$B$6*Assumptions!$B$13+Assumptions!$B$8*Assumptions!$B$14+Assumptions!$B$10*Assumptions!$B$15) | D17: =D15*(Assumptions!$B$6*Assumptions!$B$13+Assumptions!$B$8*Assumptions!$B$14+Assumptions!$B$10*Assumptions!$B$15)
A18: Total revenue | B18: =B17 | C18: =C17 | D18: =D17
A19: Total expenses | B19: =B16+B17 | C19: =C16+C17 | D19: =D16+D17
A20: Net profit | B20: =Assumptions!$B$24 | C20: =Assumptions!$B$24 | D20: =Assumptions!$B$24
B21: =B19-B20 | C21: =C19-C20 | D21: =D19-D20
A22: MONTH 3
A23: Total clients acquired | B23: 6 | C23: 6 | D23: 9
A24: Total setup revenue | B24: =B23*(Assumptions!$B$5*Assumptions!$B$13+Assumptions!$B$7*Assumptions!$B$14+Assumptions!$B$9*Assumptions!$B$15) | C24: =C23*(Assumptions!$B$5*Assumptions!$B$13+Assumptions!$B$7*Assumptions!$B$14+Assumptions!$B$9*Assumptions!$B$15) | D24: =D23*(Assumptions!$B$5*Assumptions!$B$13+Assumptions!$B$7*Assumptions!$B$14+Assumptions!$B$9*Assumptions!$B$15)
A25: Ending MRR | B25: =B23*(Assumptions!$B$6*Assumptions!$B$13+Assumptions!$B$8*Assumptions!$B$14+Assumptions!$B$10*Assumptions!$B$15) | C25: =C23*(Assumptions!$B$6*Assumptions!$B$13+Assumptions!$B$8*Assumptions!$B$14+Assumptions!$B$10*Assumptions!$B$15) | D25: =D23*(Assumptions!$B$6*Assumptions!$B$13+Assumptions!$B$8*Assumptions!$B$14+Assumptions!$B$10*Assumptions!$B$15)
A26: Total revenue | B26: =B25 | C26: =C25 | D26: =D25
A27: Total expenses | B27: =B24+B25 | C27: =C24+C25 | D27: =D24+D25
A28: Net profit | B28: =Assumptions!$B$24 | C28: =Assumptions!$B$24 | D28: =Assumptions!$B$24
B29: =B27-B28 | C29: =C27-C28 | D29: =D27-D28

Sheet Monthly P&L
A1: MONTHLY P&L STATEMENT
B2: Month 1 | C2: Month 2 | D2: Month 3
A3: REVENUE
A4: Setup Fees
A5: Monthly Recurring Revenue | B5: =2*(Assumptions!$B$5*Assumptions!$B$13+Assumptions!$B$7*Assumptions!$B$14+Assumptions!$B$9*Assumptions!$B$15) | C5: =4*(Assumptions!$B$5*Assumptions!$B$13+Assumptions!$B$7*Assumptions!$B$14+Assumptions!$B$9*Assumptions!$B$15) | D5: =6*(Assumptions!$B$5*Assumptions!$B$13+Assumptions!$B$7*Assumptions!$B$14+Assumptions!$B$9*Assumptions!$B$15)
A6: Add-on Revenue (domains, email) | B6: ='Week-by-Week'!E8 | C6: ='Week-by-Week'!I8 | D6: ='Week-by-Week'!M8
B7: 0 | C7: =B7*1.5 | D7: =C7*1.5
A8: Total Revenue | B8: =SUM(B5:B7) | C8: =SUM(C5:C7) | D8: =SUM(D5:D7)
A10: EXPENSES
A11: Claude Max | B11: 200 | C11: 200 | D11: 200
A12: Lovable | B12: 50 | C12: 50 | D12: 50
A13: Instantly.ai | B13: 37 | C13: 37 | D13: 37
A14: Google Workspace | B14: 14 | C14: 14 | D14: 14
A15: Outscraper | B15: 10 | C15: 10 | D15: 10
A16: Domains | B16: 3 | C16: 3 | D16: 3
A18: Total Expenses | B18: =SUM(B11:B16) | C18: =SUM(C11:C16) | D18: =SUM(D11:D16)
A20: GROSS PROFIT | B20: =B8-B17 | C20: =C8-C17 | D20: =D8-D17
A21: Profit Margin % | B21: =IF(B8=0,0,B19/B8) | C21: =IF(C8=0,0,C19/C8) | D21: =IF(D8=0,0,D19/D8)

Sheet Revenue Milestones
A1: REVENUE MILESTONES
A2: Milestone | B2: Clients Needed | C2: Estimated Timeline
A3: First client | B3: 1 | C3: Week 3-4
A4: Break even ($324/mo) | B4: =ROUND(324/(Assumptions!$B$6*Assumptions!$B$13+Assumptions!$B$8*Assumptions!$B$14+Assumptions!$B$10*Assumptions!$B$15),1) | C4: Month 1
A5: $1,000 MRR | B5: =ROUND(1000/(Assumptions!$B$6*Assumptions!$B$13+Assumptions!$B$8*Assumptions!$B$14+Assumptions!$B$10*Assumptions!$B$15),0) | C5: Month 2-3
A6: $2,500 MRR | B6: =ROUND(2500/(Assumptions!$B$6*Assumptions!$B$13+Assumptions!$B$8*Assumptions!$B$14+Assumptions!$B$10*Assumptions!$B$15),0) | C6: Month 3+
A7: $5,000 MRR | B7: =ROUND(5000/(Assumptions!$B$6*Assumptions!$B$13+Assumptions!$B$8*Assumptions!$B$14+Assumptions!$B$10*Assumptions!$B$15),0) | C7: Month 5-6
A8: $10,000 MRR | B8: =ROUND(10000/(Assumptions!$B$6*Assumptions!$B$13+Assumptions!$B$8*Assumptions!$B$14+Assumptions!$B$10*Assumptions!$B$15),0) | C8: Month 8-9
A10: NOTES
A11: Weighted avg MRR per client | B11: =Assumptions!$B$6*Assumptions!$B$13+Assumptions!$B$8*Assumptions!$B$14+Assumptions!$B$10*Assumptions!$B$15
A12: Break-even clients (monthly) | B12: =ROUND(Assumptions!$B$24/B11,1)
A13: All revenue at 10% reply rate assumes email marketing is working
